featureflag/__init__.py
featureflag/admin.py
featureflag/apps.py
featureflag/conf.py
featureflag/migrations/0001_initial.py
featureflag/migrations/__init__.py
featureflag/models.py
featureflag/utils.py
featureflag-0.1.0.dist-info/WHEEL
featureflag-0.1.0.dist-info/METADATA
featureflag-0.1.0.dist-info/RECORD
