Metadata-Version: 2.1
Name: featureflag
Version: 0.1.0
Summary: Object based feature flags for django
Author: Winston Ferreira
Author-email: winstonf88@gmail.com
Requires-Python: >=3.6,<4.0
Classifier: Programming Language :: Python :: 3
Classifier: Programming Language :: Python :: 3.6
Classifier: Programming Language :: Python :: 3.7
Classifier: Programming Language :: Python :: 3.8
Classifier: Programming Language :: Python :: 3.9
Requires-Dist: Django (>=3.1.3,<4.0.0)
